yapcad/__init__.py
yapcad/combine.py
yapcad/drawable.py
yapcad/ezdxf_drawable.py
yapcad/geom.py
yapcad/geom3d.py
yapcad/geom3d_util.py
yapcad/geom_util.py
yapcad/geometry.py
yapcad/geometry_checks.py
yapcad/geometry_utils.py
yapcad/mesh.py
yapcad/metadata.py
yapcad/octtree.py
yapcad/poly.py
yapcad/pyglet_drawable.py
yapcad/spline.py
yapcad/triangulator.py
yapcad/xform.py
yapcad/boolean/__init__.py
yapcad/boolean/native.py
yapcad/boolean/trimesh_engine.py
yapcad/io/__init__.py
yapcad/io/step.py
yapcad/io/stl.py
yapcad-0.5.1.dist-info/licenses/AUTHORS.rst
yapcad-0.5.1.dist-info/licenses/LICENSE
yapcad-0.5.1.dist-info/licenses/LICENSE.txt
yapcad-0.5.1.dist-info/METADATA
yapcad-0.5.1.dist-info/WHEEL
yapcad-0.5.1.dist-info/top_level.txt
yapcad-0.5.1.dist-info/RECORD
