Metadata-Version: 2.4
Name: yapCAD
Version: 0.5.1
Summary: yet another procedural CAD and computational geometry system
Author-email: Richard DeVaul <richard.devaul@gmail.com>
Project-URL: Homepage, https://github.com/rdevaul/yapCAD/
Project-URL: Documentation, https://yapcad.readthedocs.io/en/latest/
Classifier: Programming Language :: Python :: 3
Classifier: License :: OSI Approved :: MIT License
Classifier: Operating System :: OS Independent
Requires-Python: >=3.10
License-File: LICENSE
License-File: LICENSE.txt
License-File: AUTHORS.rst
Requires-Dist: ezdxf>=1.1
Requires-Dist: pyglet<2,>=1.5
Requires-Dist: mpmath>=1.2
Requires-Dist: numpy>=1.22
Requires-Dist: mapbox-earcut>=1.0.3
Requires-Dist: pyobjc-core; platform_system == "Darwin"
Requires-Dist: pyobjc-framework-Cocoa; platform_system == "Darwin"
Requires-Dist: pyobjc-framework-Quartz; platform_system == "Darwin"
Provides-Extra: tests
Requires-Dist: pytest; extra == "tests"
Requires-Dist: pytest-cov; extra == "tests"
Provides-Extra: meshcheck
Requires-Dist: trimesh>=4.0; extra == "meshcheck"
Requires-Dist: pymeshfix>=0.16; extra == "meshcheck"
Dynamic: license-file
